BMIckwrlTest001/BMI_test.py
BMIckwrlTest001-0.0.0.2.dist-info/METADATA
BMIckwrlTest001-0.0.0.2.dist-info/WHEEL
BMIckwrlTest001-0.0.0.2.dist-info/top_level.txt
BMIckwrlTest001-0.0.0.2.dist-info/RECORD
