Metadata-Version: 2.1
Name: BMIckwrlTest001
Version: 0.0.0.2
Summary: BMI test
Home-page: UNKNOWN
Author: mmopg42
Author-email: mmopg42@gmail.com
License: MIT
Platform: UNKNOWN
Requires-Python: >=3
